arboreto/__init__.py
arboreto/algo.py
arboreto/core.py
arboreto/utils.py
tests/__init__.py
tests/test_algo.py
tests/test_core.py
arboreto-0.1.6.dist-info/LICENSE.txt
arboreto-0.1.6.dist-info/METADATA
arboreto-0.1.6.dist-info/WHEEL
arboreto-0.1.6.dist-info/top_level.txt
arboreto-0.1.6.dist-info/RECORD
