Metadata-Version: 2.1
Name: arboreto
Version: 0.1.6
Summary: Scalable gene regulatory network inference using tree-based ensemble regressors
Home-page: https://github.com/aertslab/arboreto
Author: Thomas Moerman
Author-email: thomas.moerman@gmail.com
License: BSD 3-Clause License
Keywords: gene,regulatory,network,inference,regression,ensemble,scalable,dask
Platform: any
Requires-Dist: dask[complete]
Requires-Dist: distributed
Requires-Dist: numpy (>=1.16.5)
Requires-Dist: pandas
Requires-Dist: scikit-learn
Requires-Dist: scipy
